xgbatch/__init__.py
xgbatch/client.py
xgbatch/common.py
xgbatch/server.py
xgbatch-0.0.2.dist-info/LICENSE.txt
xgbatch-0.0.2.dist-info/METADATA
xgbatch-0.0.2.dist-info/WHEEL
xgbatch-0.0.2.dist-info/top_level.txt
xgbatch-0.0.2.dist-info/RECORD
