Metadata-Version: 2.1
Name: xgbatch
Version: 0.0.2
Summary: High Performance Serving for XGBoost
Home-page: https://github.com/ehenry2/xgbatch
Author: Eric Henry
License: UNKNOWN
Platform: UNKNOWN
Classifier: Programming Language :: Python :: 3
Classifier: License :: OSI Approved :: MIT License
Classifier: Operating System :: OS Independent
Requires-Python: >=3.6
Requires-Dist: pyarrow (>=3.0.0)
Requires-Dist: xgboost (>=1.0.0)
Requires-Dist: numpy (>=1.0.0)
